geoimage/__init__.py
geoimage/geoimage.py
geoimage-0.5.dist-info/DESCRIPTION.rst
geoimage-0.5.dist-info/METADATA
geoimage-0.5.dist-info/RECORD
geoimage-0.5.dist-info/WHEEL
geoimage-0.5.dist-info/metadata.json
geoimage-0.5.dist-info/pbr.json
geoimage-0.5.dist-info/top_level.txt
