Metadata-Version: 2.0
Name: geoimage
Version: 0.5
Summary: A utility to geolocate images
Home-page: https://github.com/suvarchal/GeoLocateImage
Author: Suvarchal Kumar Cheedela
Author-email: suvarchal.kumar@gmail.com
License: MIT
Platform: UNKNOWN
Classifier: Development Status :: 4 - Beta
Classifier: Topic :: Software Development :: Build Tools
Classifier: License :: OSI Approved :: MIT License
Classifier: Programming Language :: Python :: 2
Classifier: Programming Language :: Python :: 2.7
Classifier: Programming Language :: Python :: 3
Requires-Dist: PIL
